LASER/__init__.py
LASER/data/__init__.py
LASER/data/async_data.py
LASER/data/data_sampler.py
LASER/data/dynamic_dataset.py
LASER/optims/__init__.py
LASER/optims/args.py
LASER/optims/fp16_optimizer.py
LASER/optims/lr_schedulers.py
LASER/optims/xadam.py
LASER/training/__init__.py
LASER/training/_utils.py
LASER/training/args.py
LASER/training/dist_launcher.py
LASER/training/optimizer_utils.py
LASER/training/trainer.py
LASER/utils/__init__.py
LASER/utils/argument_types.py
LASER/utils/logger_util.py
LASER-0.0.5.dist-info/LICENSE
LASER-0.0.5.dist-info/METADATA
LASER-0.0.5.dist-info/WHEEL
LASER-0.0.5.dist-info/top_level.txt
LASER-0.0.5.dist-info/RECORD
