Metadata-Version: 2.1
Name: LASER
Version: 0.0.5
Summary: A toolkit for large scale distributed training
Home-page: https://github.com/BigBird01/LASER
Author: Pengcheng He
Author-email: penhe@microsoft.com
License: MIT
Keywords: Distributed deep learning
Platform: UNKNOWN
Classifier: Programming Language :: Python :: 3
Classifier: License :: OSI Approved :: MIT License
Classifier: Operating System :: OS Independent
Requires-Python: >=3.6
Requires-Dist: numpy
Requires-Dist: pytest
Requires-Dist: regex
Requires-Dist: tqdm
Requires-Dist: ujson
Requires-Dist: psutil
Requires-Dist: torch
Provides-Extra: docs
Requires-Dist: recommonmark ; extra == 'docs'
Requires-Dist: sphinx ; extra == 'docs'
Requires-Dist: sphinx-markdown-tables ; extra == 'docs'
Requires-Dist: sphinx-rtd-theme ; extra == 'docs'
